random_password/__init__.py
random_password/random_password.py
tests/__init__.py
tests/test_random_password.py
random_password_generator2024-0.1.0.dist-info/LICENSE
random_password_generator2024-0.1.0.dist-info/METADATA
random_password_generator2024-0.1.0.dist-info/WHEEL
random_password_generator2024-0.1.0.dist-info/top_level.txt
random_password_generator2024-0.1.0.dist-info/RECORD
