Metadata-Version: 2.1
Name: random_password_generator2024
Version: 0.1.0
Summary: A random password generator
Home-page: https://github.com/DeusExTaco/RandomPasswordGenerator
Author: Adam Hernandez
Author-email: adam@hernandez.ac
Classifier: Programming Language :: Python :: 3
Classifier: License :: OSI Approved :: MIT License
Classifier: Operating System :: OS Independent
Requires-Python: >=3.6
License-File: LICENSE
